README.md
setup.py
cocorf/__init__.py
cocorf/model_filter.py
cocorf/multihead_model.py
cocorf/rule_filter.py
cocorf.egg-info/PKG-INFO
cocorf.egg-info/SOURCES.txt
cocorf.egg-info/dependency_links.txt
cocorf.egg-info/requires.txt
cocorf.egg-info/top_level.txt