Metadata-Version: 2.1
Name: cocorf
Version: 0.1
Summary: Comment-based codebase refining framework
Home-page: UNKNOWN
Author-email: Zxqinn@gmail.com
License: UNKNOWN
Platform: UNKNOWN
Classifier: Programming Language :: Python :: 3
Classifier: License :: OSI Approved :: MIT License
